odoo/addons/web_decimal_numpad_dot/README.rst
odoo/addons/web_decimal_numpad_dot/__init__.py
odoo/addons/web_decimal_numpad_dot/__manifest__.py
odoo/addons/web_decimal_numpad_dot/i18n/web_decimal_numpad_dot.pot
odoo/addons/web_decimal_numpad_dot/static/description/icon.png
odoo/addons/web_decimal_numpad_dot/static/src/js/numpad_dot.js
odoo/addons/web_decimal_numpad_dot/views/web_decimal_numpad_dot.xml
odoo11_addon_web_decimal_numpad_dot-11.0.1.0.3.dist-info/METADATA
odoo11_addon_web_decimal_numpad_dot-11.0.1.0.3.dist-info/RECORD
odoo11_addon_web_decimal_numpad_dot-11.0.1.0.3.dist-info/WHEEL
odoo11_addon_web_decimal_numpad_dot-11.0.1.0.3.dist-info/top_level.txt
